LICENSE.txt
README.md
mandos/__init__.py
mandos/api.py
mandos/cli.py
mandos/model/__init__.py
mandos/model/caches.py
mandos/model/settings.py
mandos/model/targets.py
mandos/model/taxonomy.py
mandos/resources/7742.tab.gz
mandos/search/__init__.py
mandos/search/activity_search.py
mandos/search/atc_search.py
mandos/search/indication_search.py
mandos/search/mechanism_search.py
mandos/search/protein_search.py
mandos-0.1.0.dist-info/entry_points.txt
mandos-0.1.0.dist-info/LICENSE.txt
mandos-0.1.0.dist-info/WHEEL
mandos-0.1.0.dist-info/METADATA
mandos-0.1.0.dist-info/RECORD
