Metadata-Version: 2.1
Name: mandos
Version: 0.1.0
Summary: Get the biological targets of compounds.
Home-page: https://github.com/dmyersturnbull/mandos
License: Apache-2.0
Keywords: cheminformatics,chembl
Author: Douglas Myers-Turnbull
Maintainer: Douglas Myers-Turnbull
Requires-Python: >=3.8,<4
Classifier: Development Status :: 2 - Pre-Alpha
Classifier: Intended Audience :: Developers
Classifier: Intended Audience :: Science/Research
Classifier: License :: OSI Approved :: Apache Software License
Classifier: Natural Language :: English
Classifier: Operating System :: OS Independent
Classifier: Programming Language :: Python :: 3
Classifier: Programming Language :: Python :: 3 :: Only
Classifier: Programming Language :: Python :: 3.8
Classifier: Topic :: Scientific/Engineering :: Bio-Informatics
Classifier: Topic :: Scientific/Engineering :: Chemistry
Classifier: Typing :: Typed
Provides-Extra: dev
Requires-Dist: chembl-webresource-client (>=0.10,<0.11)
Requires-Dist: pandas (>=1.1,<2.0)
Requires-Dist: pocketutils (>=0.3.2,<0.4)
Requires-Dist: requests (>=2.24,<3.0)
Requires-Dist: tomlkit (>=0.7,<1.0)
Requires-Dist: tqdm (>=4.48,<5.0)
Requires-Dist: typer[colorama] (>=0.3,<1.0)
Project-URL: CI, https://github.com/dmyersturnbull/mandos/actions
Project-URL: Documentation, https://mandos-chem.readthedocs.io
Project-URL: Issues, https://github.com/dmyersturnbull/mandos/issues
Project-URL: Repository, https://github.com/dmyersturnbull/mandos
